pyxllib/__init__.py
pyxllib/xl.py
pyxllib/xlcv.py
pyxllib/xlwork.py
pyxllib/ai/__init__.py
pyxllib/ai/chat.py
pyxllib/algo/__init__.py
pyxllib/algo/disjoint.py
pyxllib/algo/geo.py
pyxllib/algo/intervals.py
pyxllib/algo/matcher.py
pyxllib/algo/newbie.py
pyxllib/algo/pupil.py
pyxllib/algo/shapelylib.py
pyxllib/algo/specialist.py
pyxllib/algo/stat.py
pyxllib/algo/treelib.py
pyxllib/algo/unitlib.py
pyxllib/autogui/__init__.py
pyxllib/autogui/activewin.py
pyxllib/autogui/all.py
pyxllib/autogui/anlib.py
pyxllib/autogui/autogui.py
pyxllib/autogui/uiautolib.py
pyxllib/autogui/virtualkey.py
pyxllib/autogui/wechat.py
pyxllib/autogui/wechat_msg.py
pyxllib/autogui/wxautolib.py
pyxllib/cv/__init__.py
pyxllib/cv/expert.py
pyxllib/cv/imfile.py
pyxllib/cv/imhash.py
pyxllib/cv/pupil.py
pyxllib/cv/rgbfmt.py
pyxllib/cv/slidercaptcha.py
pyxllib/cv/trackbartools.py
pyxllib/cv/xlcvlib.py
pyxllib/cv/xlpillib.py
pyxllib/data/__init__.py
pyxllib/data/echarts.py
pyxllib/data/json2table.py
pyxllib/data/jsonlib.py
pyxllib/data/oss.py
pyxllib/data/pglib.py
pyxllib/data/sqlite.py
pyxllib/data/sqllib.py
pyxllib/ext/JLineViewer.py
pyxllib/ext/__init__.py
pyxllib/ext/demolib.py
pyxllib/ext/drissionlib.py
pyxllib/ext/kq5034lib.py
pyxllib/ext/qt.py
pyxllib/ext/robustprocfile.py
pyxllib/ext/seleniumlib.py
pyxllib/ext/tk.py
pyxllib/ext/unixlib.py
pyxllib/ext/utools.py
pyxllib/ext/webhook.py
pyxllib/ext/win32lib.py
pyxllib/ext/wjxlib.py
pyxllib/ext/wpsapi.py
pyxllib/ext/yuquelib.py
pyxllib/file/__init__.py
pyxllib/file/docxlib.py
pyxllib/file/gitlib.py
pyxllib/file/libreoffice.py
pyxllib/file/movielib.py
pyxllib/file/newbie.py
pyxllib/file/onenotelib.py
pyxllib/file/pdflib.py
pyxllib/file/pupil.py
pyxllib/file/xlsxlib.py
pyxllib/file/xlsyncfile.py
pyxllib/file/packlib/__init__.py
pyxllib/file/packlib/zipfile.py
pyxllib/file/specialist/__init__.py
pyxllib/file/specialist/dirlib.py
pyxllib/file/specialist/download.py
pyxllib/file/specialist/filelib.py
pyxllib/prog/__init__.py
pyxllib/prog/cachetools.py
pyxllib-4.33.2.dist-info/METADATA
pyxllib-4.33.2.dist-info/WHEEL
pyxllib-4.33.2.dist-info/licenses/LICENSE
pyxllib-4.33.2.dist-info/RECORD
